{
  "updated": "2026-07-08",
  "stocks": [
    {
      "code": "0001A0",
      "name": "덕양에너젠",
      "market": "코스닥",
      "listing_date": "2026-01-30",
      "shares": 24791195,
      "close_price": 34850,
      "events": [
        {
          "period": "15일",
          "date": "2026-02-14",
          "date_display": "2026-02-14",
          "tradable_date": "2026-02-14",
          "qty": 1767670,
          "pct": 7.13,
          "type": "IPO확약",
          "category": "IPO기관",
          "status": "확정(경과)",
          "source": "DART",
          "source_label": "증권발행실적보고서",
          "rcp": "20260123000364",
          "api_checked": false,
          "api_return_date": null,
          "api_return_qty": null,
          "api_source": "공공데이터포털 getLockUpRetuInfo_V3",
          "holder_name": null,
          "reason": null
        },
        {
          "period": "1개월",
          "date": "2026-02-28",
          "date_display": "2026-02-28",
          "tradable_date": "2026-02-28",
          "qty": 447675,
          "pct": 1.81,
          "type": "IPO확약",
          "category": "IPO기관",
          "status": "확정(경과)",
          "source": "DART",
          "source_label": "증권발행실적보고서",
          "rcp": "20260123000364",
          "api_checked": false,
          "api_return_date": null,
          "api_return_qty": null,
          "api_source": "공공데이터포털 getLockUpRetuInfo_V3",
          "holder_name": null,
          "reason": null
        },
        {
          "period": "1개월",
          "date": "2026-03-03",
          "date_display": "2026-03-03",
          "tradable_date": "2026-03-03",
          "qty": 5955,
          "pct": 0.02,
          "type": "보호예수",
          "category": "구주·보호예수",
          "status": "반환확인",
          "source": "투자설명서",
          "source_label": "투자설명서 유통가능 요약표",
          "rcp": "20260119000299",
          "api_checked": true,
          "api_return_date": "2026-03-03",
          "api_return_qty": 5955,
          "api_source": "공공데이터포털 getLockUpRetuInfo_V3",
          "holder_name": "기관투자가",
          "reason": "기관투자가"
        },
        {
          "period": "3개월",
          "date": "2026-04-30",
          "date_display": "2026-04-30",
          "tradable_date": "2026-04-30",
          "qty": 1256610,
          "pct": 5.07,
          "type": "IPO확약",
          "category": "IPO기관",
          "status": "확정(경과)",
          "source": "DART",
          "source_label": "증권발행실적보고서",
          "rcp": "20260123000364",
          "api_checked": false,
          "api_return_date": null,
          "api_return_qty": null,
          "api_source": "공공데이터포털 getLockUpRetuInfo_V3",
          "holder_name": null,
          "reason": null
        },
        {
          "period": "3개월",
          "date": "2026-04-30",
          "date_display": "2026-04-30",
          "tradable_date": "2026-04-30",
          "qty": 100000,
          "pct": 0.4,
          "type": "보호예수",
          "category": "구주·보호예수",
          "status": "반환확인",
          "source": "투자설명서",
          "source_label": "투자설명서 유통가능 요약표",
          "rcp": "20260119000299",
          "api_checked": true,
          "api_return_date": "2026-04-30",
          "api_return_qty": 100000,
          "api_source": "공공데이터포털 getLockUpRetuInfo_V3",
          "holder_name": "상장주선인(국내기업)",
          "reason": "상장주선인(국내기업)"
        },
        {
          "period": "6개월",
          "date": "2026-07-30",
          "date_display": "2026-07-30",
          "tradable_date": "2026-07-30",
          "qty": 371790,
          "pct": 1.5,
          "type": "IPO확약",
          "category": "IPO기관",
          "status": "예정",
          "source": "DART",
          "source_label": "증권발행실적보고서",
          "rcp": "20260123000364",
          "api_checked": false,
          "api_return_date": null,
          "api_return_qty": null,
          "api_source": "공공데이터포털 getLockUpRetuInfo_V3",
          "holder_name": null,
          "reason": null
        },
        {
          "period": "6개월",
          "date": "2026-07-30",
          "date_display": "2026-07-30",
          "tradable_date": "2026-07-30",
          "qty": 6631546,
          "pct": 26.75,
          "type": "보호예수",
          "category": "구주·보호예수",
          "status": "예정",
          "source": "투자설명서",
          "source_label": "투자설명서 유통가능 요약표",
          "rcp": "20260119000299",
          "api_checked": false,
          "api_return_date": null,
          "api_return_qty": null,
          "api_source": "공공데이터포털 getLockUpRetuInfo_V3",
          "holder_name": null,
          "reason": null
        },
        {
          "period": "12개월",
          "date": "2027-01-30",
          "date_display": "2027-01-30",
          "tradable_date": "2027-01-30",
          "qty": 184979,
          "pct": 0.75,
          "type": "보호예수",
          "category": "구주·보호예수",
          "status": "예정",
          "source": "투자설명서",
          "source_label": "투자설명서 유통가능 요약표",
          "rcp": "20260119000299",
          "api_checked": false,
          "api_return_date": null,
          "api_return_qty": null,
          "api_source": "공공데이터포털 getLockUpRetuInfo_V3",
          "holder_name": null,
          "reason": null
        },
        {
          "period": "30개월",
          "date": "2028-07-30",
          "date_display": "2028-07-30",
          "tradable_date": "2028-07-30",
          "qty": 9924237,
          "pct": 40.03,
          "type": "보호예수",
          "category": "구주·보호예수",
          "status": "예정",
          "source": "투자설명서",
          "source_label": "투자설명서 유통가능 요약표",
          "rcp": "20260119000299",
          "api_checked": false,
          "api_return_date": null,
          "api_return_qty": null,
          "api_source": "공공데이터포털 getLockUpRetuInfo_V3",
          "holder_name": null,
          "reason": null
        }
      ],
      "holders": []
    },
    {
      "code": "279570",
      "name": "케이뱅크",
      "market": "코스피",
      "listing_date": "2026-03-05",
      "shares": 405695151,
      "close_price": 8330,
      "events": [
        {
          "period": "15일",
          "date": "2026-03-20",
          "date_display": "2026-03-20",
          "tradable_date": "2026-03-20",
          "qty": 5211720,
          "pct": 1.28,
          "type": "IPO확약",
          "category": "IPO기관",
          "status": "확정(경과)",
          "source": "DART",
          "source_label": "증권발행실적보고서",
          "rcp": "20260225005229",
          "api_checked": false,
          "api_return_date": null,
          "api_return_qty": null,
          "api_source": "공공데이터포털 getLockUpRetuInfo_V3",
          "holder_name": null,
          "reason": null
        },
        {
          "period": "1개월",
          "date": "2026-04-05",
          "date_display": "2026-04-05",
          "tradable_date": "2026-04-05",
          "qty": 3295900,
          "pct": 0.81,
          "type": "IPO확약",
          "category": "IPO기관",
          "status": "확정(경과)",
          "source": "DART",
          "source_label": "증권발행실적보고서",
          "rcp": "20260225005229",
          "api_checked": false,
          "api_return_date": null,
          "api_return_qty": null,
          "api_source": "공공데이터포털 getLockUpRetuInfo_V3",
          "holder_name": null,
          "reason": null
        },
        {
          "period": "3개월",
          "date": "2026-06-05",
          "date_display": "2026-06-05",
          "tradable_date": "2026-06-05",
          "qty": 473660,
          "pct": 0.12,
          "type": "IPO확약",
          "category": "IPO기관",
          "status": "확정(경과)",
          "source": "DART",
          "source_label": "증권발행실적보고서",
          "rcp": "20260225005229",
          "api_checked": false,
          "api_return_date": null,
          "api_return_qty": null,
          "api_source": "공공데이터포털 getLockUpRetuInfo_V3",
          "holder_name": null,
          "reason": null
        },
        {
          "period": "3개월",
          "date": "2026-06-05",
          "date_display": "2026-06-05",
          "tradable_date": "2026-06-05",
          "qty": 35759040,
          "pct": 8.81,
          "type": "보호예수",
          "category": "구주·보호예수",
          "status": "반환확인",
          "source": "투자설명서",
          "source_label": "투자설명서 유통가능 요약표",
          "rcp": "20260212001582",
          "api_checked": true,
          "api_return_date": "2026-06-05",
          "api_return_qty": 35759040,
          "api_source": "공공데이터포털 getLockUpRetuInfo_V3",
          "holder_name": "기타 보호예수 필요 주주",
          "reason": "기타 보호예수 필요 주주"
        },
        {
          "period": "6개월",
          "date": "2026-09-05",
          "date_display": "2026-09-05",
          "tradable_date": "2026-09-05",
          "qty": 10808410,
          "pct": 2.66,
          "type": "IPO확약",
          "category": "IPO기관",
          "status": "예정",
          "source": "DART",
          "source_label": "증권발행실적보고서",
          "rcp": "20260225005229",
          "api_checked": false,
          "api_return_date": null,
          "api_return_qty": null,
          "api_source": "공공데이터포털 getLockUpRetuInfo_V3",
          "holder_name": null,
          "reason": null
        },
        {
          "period": "6개월",
          "date": "2026-09-05",
          "date_display": "2026-09-05",
          "tradable_date": "2026-09-05",
          "qty": 83775566,
          "pct": 20.65,
          "type": "보호예수",
          "category": "구주·보호예수",
          "status": "예정",
          "source": "투자설명서",
          "source_label": "투자설명서 유통가능 요약표",
          "rcp": "20260212001582",
          "api_checked": false,
          "api_return_date": null,
          "api_return_qty": null,
          "api_source": "공공데이터포털 getLockUpRetuInfo_V3",
          "holder_name": null,
          "reason": null
        },
        {
          "period": "1년",
          "date": "2027-03-05",
          "date_display": "2027-03-05",
          "tradable_date": "2027-03-05",
          "qty": 138690193,
          "pct": 34.19,
          "type": "보호예수",
          "category": "구주·보호예수",
          "status": "예정",
          "source": "투자설명서",
          "source_label": "투자설명서 유통가능 요약표",
          "rcp": "20260212001582",
          "api_checked": false,
          "api_return_date": null,
          "api_return_qty": null,
          "api_source": "공공데이터포털 getLockUpRetuInfo_V3",
          "holder_name": null,
          "reason": null
        }
      ],
      "holders": []
    },
    {
      "code": "458350",
      "name": "에스팀",
      "market": "코스닥",
      "listing_date": "2026-03-06",
      "shares": 8683200,
      "close_price": 34000,
      "events": [
        {
          "period": "15일",
          "date": "2026-03-23",
          "date_display": "2026-03-23",
          "tradable_date": "2026-03-23",
          "qty": 582582,
          "pct": 6.71,
          "type": "IPO확약",
          "category": "IPO기관",
          "status": "확정(경과)",
          "source": "DART",
          "source_label": "증권발행실적보고서",
          "rcp": "20260226005084",
          "api_checked": false,
          "api_return_date": null,
          "api_return_qty": null,
          "api_source": "공공데이터포털 getLockUpRetuInfo_V3",
          "holder_name": null,
          "reason": null
        },
        {
          "period": "1개월",
          "date": "2026-04-06",
          "date_display": "2026-04-06",
          "tradable_date": "2026-04-06",
          "qty": 185497,
          "pct": 2.14,
          "type": "IPO확약",
          "category": "IPO기관",
          "status": "확정(경과)",
          "source": "DART",
          "source_label": "증권발행실적보고서",
          "rcp": "20260226005084",
          "api_checked": false,
          "api_return_date": null,
          "api_return_qty": null,
          "api_source": "공공데이터포털 getLockUpRetuInfo_V3",
          "holder_name": null,
          "reason": null
        },
        {
          "period": "3개월",
          "date": "2026-06-08",
          "date_display": "2026-06-08",
          "tradable_date": "2026-06-08",
          "qty": 54000,
          "pct": 0.62,
          "type": "IPO확약",
          "category": "IPO기관",
          "status": "반환확인_API수정",
          "source": "DART",
          "source_label": "증권발행실적보고서",
          "rcp": "20260226005084",
          "api_checked": true,
          "api_return_date": "2026-06-08",
          "api_return_qty": 54000,
          "api_source": "공공데이터포털 getLockUpRetuInfo_V3",
          "holder_name": "상장주선인(국내기업)",
          "reason": "상장주선인(국내기업)"
        },
        {
          "period": "6개월",
          "date": "2026-09-07",
          "date_display": "2026-09-07",
          "tradable_date": "2026-09-07",
          "qty": 96826,
          "pct": 1.12,
          "type": "IPO확약",
          "category": "IPO기관",
          "status": "예정",
          "source": "DART",
          "source_label": "증권발행실적보고서",
          "rcp": "20260226005084",
          "api_checked": false,
          "api_return_date": null,
          "api_return_qty": null,
          "api_source": "공공데이터포털 getLockUpRetuInfo_V3",
          "holder_name": null,
          "reason": null
        }
      ],
      "holders": []
    },
    {
      "code": "0011A0",
      "name": "액스비스",
      "market": "코스닥",
      "listing_date": "2026-03-09",
      "shares": 9333740,
      "close_price": 46000,
      "events": [
        {
          "period": "15일",
          "date": "2026-03-24",
          "date_display": "2026-03-24",
          "tradable_date": "2026-03-24",
          "qty": 161110,
          "pct": 1.73,
          "type": "IPO확약",
          "category": "IPO기관",
          "status": "확정(경과)",
          "source": "DART",
          "source_label": "증권발행실적보고서",
          "rcp": "20260226002277",
          "api_checked": false,
          "api_return_date": null,
          "api_return_qty": null,
          "api_source": "공공데이터포털 getLockUpRetuInfo_V3",
          "holder_name": null,
          "reason": null
        },
        {
          "period": "1개월",
          "date": "2026-04-09",
          "date_display": "2026-04-09",
          "tradable_date": "2026-04-09",
          "qty": 239250,
          "pct": 2.56,
          "type": "IPO확약",
          "category": "IPO기관",
          "status": "확정(경과)",
          "source": "DART",
          "source_label": "증권발행실적보고서",
          "rcp": "20260226002277",
          "api_checked": false,
          "api_return_date": null,
          "api_return_qty": null,
          "api_source": "공공데이터포털 getLockUpRetuInfo_V3",
          "holder_name": null,
          "reason": null
        },
        {
          "period": "1개월",
          "date": "2026-04-09",
          "date_display": "2026-04-09",
          "tradable_date": "2026-04-09",
          "qty": 524543,
          "pct": 5.62,
          "type": "보호예수",
          "category": "구주·보호예수",
          "status": "반환확인_API수정",
          "source": "투자설명서",
          "source_label": "투자설명서 유통가능 요약표",
          "rcp": "20260219002071",
          "api_checked": true,
          "api_return_date": "2026-04-09",
          "api_return_qty": 524543,
          "api_source": "공공데이터포털 getLockUpRetuInfo_V3",
          "holder_name": "기타 보호예수 필요 주주",
          "reason": "기타 보호예수 필요 주주"
        },
        {
          "period": "2개월",
          "date": "2026-05-11",
          "date_display": "2026-05-11",
          "tradable_date": "2026-05-11",
          "qty": 224803,
          "pct": 2.41,
          "type": "보호예수",
          "category": "구주·보호예수",
          "status": "반환확인",
          "source": "투자설명서",
          "source_label": "투자설명서 유통가능 요약표",
          "rcp": "20260219002071",
          "api_checked": true,
          "api_return_date": "2026-05-11",
          "api_return_qty": 224803,
          "api_source": "공공데이터포털 getLockUpRetuInfo_V3",
          "holder_name": "기타 보호예수 필요 주주",
          "reason": "기타 보호예수 필요 주주"
        },
        {
          "period": "3개월",
          "date": "2026-06-09",
          "date_display": "2026-06-09",
          "tradable_date": "2026-06-09",
          "qty": 678160,
          "pct": 7.27,
          "type": "IPO확약",
          "category": "IPO기관",
          "status": "확정(경과)",
          "source": "DART",
          "source_label": "증권발행실적보고서",
          "rcp": "20260226002277",
          "api_checked": false,
          "api_return_date": null,
          "api_return_qty": null,
          "api_source": "공공데이터포털 getLockUpRetuInfo_V3",
          "holder_name": null,
          "reason": null
        },
        {
          "period": "3개월",
          "date": "2026-06-09",
          "date_display": "2026-06-09",
          "tradable_date": "2026-06-09",
          "qty": 69000,
          "pct": 0.74,
          "type": "보호예수",
          "category": "구주·보호예수",
          "status": "반환확인",
          "source": "투자설명서",
          "source_label": "투자설명서 유통가능 요약표",
          "rcp": "20260219002071",
          "api_checked": true,
          "api_return_date": "2026-06-09",
          "api_return_qty": 69000,
          "api_source": "공공데이터포털 getLockUpRetuInfo_V3",
          "holder_name": "상장주선인(국내기업)",
          "reason": "상장주선인(국내기업)"
        },
        {
          "period": "6개월",
          "date": "2026-09-09",
          "date_display": "2026-09-09",
          "tradable_date": "2026-09-09",
          "qty": 580705,
          "pct": 6.22,
          "type": "IPO확약",
          "category": "IPO기관",
          "status": "예정",
          "source": "DART",
          "source_label": "증권발행실적보고서",
          "rcp": "20260226002277",
          "api_checked": false,
          "api_return_date": null,
          "api_return_qty": null,
          "api_source": "공공데이터포털 getLockUpRetuInfo_V3",
          "holder_name": null,
          "reason": null
        },
        {
          "period": "6개월",
          "date": "2026-09-09",
          "date_display": "2026-09-09",
          "tradable_date": "2026-09-09",
          "qty": 243767,
          "pct": 2.61,
          "type": "보호예수",
          "category": "구주·보호예수",
          "status": "예정",
          "source": "투자설명서",
          "source_label": "투자설명서 유통가능 요약표",
          "rcp": "20260219002071",
          "api_checked": false,
          "api_return_date": null,
          "api_return_qty": null,
          "api_source": "공공데이터포털 getLockUpRetuInfo_V3",
          "holder_name": null,
          "reason": null
        },
        {
          "period": "30개월",
          "date": "2028-09-09",
          "date_display": "2028-09-09",
          "tradable_date": "2028-09-09",
          "qty": 5075593,
          "pct": 54.38,
          "type": "보호예수",
          "category": "구주·보호예수",
          "status": "예정",
          "source": "투자설명서",
          "source_label": "투자설명서 유통가능 요약표",
          "rcp": "20260219002071",
          "api_checked": false,
          "api_return_date": null,
          "api_return_qty": null,
          "api_source": "공공데이터포털 getLockUpRetuInfo_V3",
          "holder_name": null,
          "reason": null
        }
      ],
      "holders": []
    },
    {
      "code": "0082N0",
      "name": "카나프테라퓨틱스",
      "market": "코스닥",
      "listing_date": "2026-03-16",
      "shares": 12956030,
      "close_price": 50600,
      "events": [
        {
          "period": "15일",
          "date": "2026-03-31",
          "date_display": "2026-03-31",
          "tradable_date": "2026-03-31",
          "qty": 119848,
          "pct": 0.93,
          "type": "IPO확약",
          "category": "IPO기관",
          "status": "확정(경과)",
          "source": "DART",
          "source_label": "증권발행실적보고서",
          "rcp": "20260310002388",
          "api_checked": false,
          "api_return_date": null,
          "api_return_qty": null,
          "api_source": "공공데이터포털 getLockUpRetuInfo_V3",
          "holder_name": null,
          "reason": null
        },
        {
          "period": "1개월",
          "date": "2026-04-16",
          "date_display": "2026-04-16",
          "tradable_date": "2026-04-16",
          "qty": 148073,
          "pct": 1.14,
          "type": "IPO확약",
          "category": "IPO기관",
          "status": "확정(경과)",
          "source": "DART",
          "source_label": "증권발행실적보고서",
          "rcp": "20260310002388",
          "api_checked": false,
          "api_return_date": null,
          "api_return_qty": null,
          "api_source": "공공데이터포털 getLockUpRetuInfo_V3",
          "holder_name": null,
          "reason": null
        },
        {
          "period": "1개월",
          "date": "2026-04-16",
          "date_display": "2026-04-16",
          "tradable_date": "2026-04-16",
          "qty": 776269,
          "pct": 5.99,
          "type": "보호예수",
          "category": "구주·보호예수",
          "status": "반환확인_API수정",
          "source": "투자설명서",
          "source_label": "투자설명서 유통가능 요약표",
          "rcp": "20260304001117",
          "api_checked": true,
          "api_return_date": "2026-04-16",
          "api_return_qty": 776269,
          "api_source": "공공데이터포털 getLockUpRetuInfo_V3",
          "holder_name": "기타 보호예수 필요 주주",
          "reason": "기타 보호예수 필요 주주"
        },
        {
          "period": "3개월",
          "date": "2026-06-16",
          "date_display": "2026-06-16",
          "tradable_date": "2026-06-16",
          "qty": 529876,
          "pct": 4.09,
          "type": "IPO확약",
          "category": "IPO기관",
          "status": "확정(경과)",
          "source": "DART",
          "source_label": "증권발행실적보고서",
          "rcp": "20260310002388",
          "api_checked": false,
          "api_return_date": null,
          "api_return_qty": null,
          "api_source": "공공데이터포털 getLockUpRetuInfo_V3",
          "holder_name": null,
          "reason": null
        },
        {
          "period": "3개월",
          "date": "2026-06-16",
          "date_display": "2026-06-16",
          "tradable_date": "2026-06-16",
          "qty": 50000,
          "pct": 0.39,
          "type": "보호예수",
          "category": "구주·보호예수",
          "status": "반환확인_API수정",
          "source": "투자설명서",
          "source_label": "투자설명서 유통가능 요약표",
          "rcp": "20260304001117",
          "api_checked": true,
          "api_return_date": "2026-06-16",
          "api_return_qty": 50000,
          "api_source": "공공데이터포털 getLockUpRetuInfo_V3",
          "holder_name": "상장주선인(국내기업)",
          "reason": "상장주선인(국내기업)"
        },
        {
          "period": "6개월",
          "date": "2026-09-16",
          "date_display": "2026-09-16",
          "tradable_date": "2026-09-16",
          "qty": 602544,
          "pct": 4.65,
          "type": "IPO확약",
          "category": "IPO기관",
          "status": "예정",
          "source": "DART",
          "source_label": "증권발행실적보고서",
          "rcp": "20260310002388",
          "api_checked": false,
          "api_return_date": null,
          "api_return_qty": null,
          "api_source": "공공데이터포털 getLockUpRetuInfo_V3",
          "holder_name": null,
          "reason": null
        },
        {
          "period": "1년",
          "date": "2027-03-16",
          "date_display": "2027-03-16",
          "tradable_date": "2027-03-16",
          "qty": 108018,
          "pct": 0.83,
          "type": "보호예수",
          "category": "구주·보호예수",
          "status": "예정",
          "source": "투자설명서",
          "source_label": "투자설명서 유통가능 요약표",
          "rcp": "20260304001117",
          "api_checked": false,
          "api_return_date": null,
          "api_return_qty": null,
          "api_source": "공공데이터포털 getLockUpRetuInfo_V3",
          "holder_name": null,
          "reason": null
        },
        {
          "period": "3년",
          "date": "2029-03-16",
          "date_display": "2029-03-16",
          "tradable_date": "2029-03-16",
          "qty": 3464888,
          "pct": 26.74,
          "type": "보호예수",
          "category": "구주·보호예수",
          "status": "예정",
          "source": "투자설명서",
          "source_label": "투자설명서 유통가능 요약표",
          "rcp": "20260304001117",
          "api_checked": false,
          "api_return_date": null,
          "api_return_qty": null,
          "api_source": "공공데이터포털 getLockUpRetuInfo_V3",
          "holder_name": null,
          "reason": null
        }
      ],
      "holders": []
    },
    {
      "code": "493280",
      "name": "아이엠바이오로직스",
      "market": "코스닥",
      "listing_date": "2026-03-20",
      "shares": 14776110,
      "close_price": 104000,
      "events": [
        {
          "period": "15일",
          "date": "2026-04-06",
          "date_display": "2026-04-06",
          "tradable_date": "2026-04-06",
          "qty": 90454,
          "pct": 0.61,
          "type": "IPO확약",
          "category": "IPO기관",
          "status": "확정(경과)",
          "source": "DART",
          "source_label": "증권발행실적보고서",
          "rcp": "20260316001249",
          "api_checked": false,
          "api_return_date": null,
          "api_return_qty": null,
          "api_source": "공공데이터포털 getLockUpRetuInfo_V3",
          "holder_name": null,
          "reason": null
        },
        {
          "period": "1개월",
          "date": "2026-04-20",
          "date_display": "2026-04-20",
          "tradable_date": "2026-04-20",
          "qty": 110652,
          "pct": 0.75,
          "type": "IPO확약",
          "category": "IPO기관",
          "status": "확정(경과)",
          "source": "DART",
          "source_label": "증권발행실적보고서",
          "rcp": "20260316001249",
          "api_checked": false,
          "api_return_date": null,
          "api_return_qty": null,
          "api_source": "공공데이터포털 getLockUpRetuInfo_V3",
          "holder_name": null,
          "reason": null
        },
        {
          "period": "1개월",
          "date": "2026-04-20",
          "date_display": "2026-04-20",
          "tradable_date": "2026-04-20",
          "qty": 1400526,
          "pct": 9.48,
          "type": "보호예수",
          "category": "구주·보호예수",
          "status": "반환확인",
          "source": "투자설명서",
          "source_label": "투자설명서 유통가능 요약표",
          "rcp": "20260310002460",
          "api_checked": true,
          "api_return_date": "2026-04-20",
          "api_return_qty": 1400526,
          "api_source": "공공데이터포털 getLockUpRetuInfo_V3",
          "holder_name": "기타 보호예수 필요 주주",
          "reason": "기타 보호예수 필요 주주"
        },
        {
          "period": "3개월",
          "date": "2026-06-22",
          "date_display": "2026-06-22",
          "tradable_date": "2026-06-22",
          "qty": 377685,
          "pct": 2.56,
          "type": "IPO확약",
          "category": "IPO기관",
          "status": "확정(경과)",
          "source": "DART",
          "source_label": "증권발행실적보고서",
          "rcp": "20260316001249",
          "api_checked": false,
          "api_return_date": null,
          "api_return_qty": null,
          "api_source": "공공데이터포털 getLockUpRetuInfo_V3",
          "holder_name": null,
          "reason": null
        },
        {
          "period": "3개월",
          "date": "2026-06-22",
          "date_display": "2026-06-22",
          "tradable_date": "2026-06-22",
          "qty": 38461,
          "pct": 0.26,
          "type": "보호예수",
          "category": "구주·보호예수",
          "status": "반환확인_API수정",
          "source": "투자설명서",
          "source_label": "투자설명서 유통가능 요약표",
          "rcp": "20260310002460",
          "api_checked": true,
          "api_return_date": "2026-06-22",
          "api_return_qty": 38461,
          "api_source": "공공데이터포털 getLockUpRetuInfo_V3",
          "holder_name": "상장주선인(국내기업)",
          "reason": "상장주선인(국내기업)"
        },
        {
          "period": "6개월",
          "date": "2026-09-21",
          "date_display": "2026-09-21",
          "tradable_date": "2026-09-21",
          "qty": 869045,
          "pct": 5.88,
          "type": "IPO확약",
          "category": "IPO기관",
          "status": "예정",
          "source": "DART",
          "source_label": "증권발행실적보고서",
          "rcp": "20260316001249",
          "api_checked": false,
          "api_return_date": null,
          "api_return_qty": null,
          "api_source": "공공데이터포털 getLockUpRetuInfo_V3",
          "holder_name": null,
          "reason": null
        },
        {
          "period": "6개월",
          "date": "2026-09-21",
          "date_display": "2026-09-21",
          "tradable_date": "2026-09-21",
          "qty": 1317497,
          "pct": 8.92,
          "type": "보호예수",
          "category": "구주·보호예수",
          "status": "예정",
          "source": "투자설명서",
          "source_label": "투자설명서 유통가능 요약표",
          "rcp": "20260310002460",
          "api_checked": false,
          "api_return_date": null,
          "api_return_qty": null,
          "api_source": "공공데이터포털 getLockUpRetuInfo_V3",
          "holder_name": null,
          "reason": null
        },
        {
          "period": "1년",
          "date": "2027-03-22",
          "date_display": "2027-03-22",
          "tradable_date": "2027-03-22",
          "qty": 1981667,
          "pct": 13.41,
          "type": "보호예수",
          "category": "구주·보호예수",
          "status": "예정",
          "source": "투자설명서",
          "source_label": "투자설명서 유통가능 요약표",
          "rcp": "20260310002460",
          "api_checked": false,
          "api_return_date": null,
          "api_return_qty": null,
          "api_source": "공공데이터포털 getLockUpRetuInfo_V3",
          "holder_name": null,
          "reason": null
        },
        {
          "period": "3년",
          "date": "2029-03-20",
          "date_display": "2029-03-20",
          "tradable_date": "2029-03-20",
          "qty": 3013500,
          "pct": 20.39,
          "type": "보호예수",
          "category": "구주·보호예수",
          "status": "예정",
          "source": "투자설명서",
          "source_label": "투자설명서 유통가능 요약표",
          "rcp": "20260310002460",
          "api_checked": false,
          "api_return_date": null,
          "api_return_qty": null,
          "api_source": "공공데이터포털 getLockUpRetuInfo_V3",
          "holder_name": null,
          "reason": null
        }
      ],
      "holders": []
    },
    {
      "code": "408470",
      "name": "한패스",
      "market": "코스닥",
      "listing_date": "2026-03-25",
      "shares": 10572000,
      "close_price": 27200,
      "events": [
        {
          "period": "15일",
          "date": "2026-04-09",
          "date_display": "2026-04-09",
          "tradable_date": "2026-04-09",
          "qty": 303734,
          "pct": 2.87,
          "type": "IPO확약",
          "category": "IPO기관",
          "status": "확정(경과)",
          "source": "DART",
          "source_label": "증권발행실적보고서",
          "rcp": "20260319000561",
          "api_checked": false,
          "api_return_date": null,
          "api_return_qty": null,
          "api_source": "공공데이터포털 getLockUpRetuInfo_V3",
          "holder_name": null,
          "reason": null
        },
        {
          "period": "1개월",
          "date": "2026-04-25",
          "date_display": "2026-04-25",
          "tradable_date": "2026-04-25",
          "qty": 57596,
          "pct": 0.54,
          "type": "IPO확약",
          "category": "IPO기관",
          "status": "확정(경과)",
          "source": "DART",
          "source_label": "증권발행실적보고서",
          "rcp": "20260319000561",
          "api_checked": false,
          "api_return_date": null,
          "api_return_qty": null,
          "api_source": "공공데이터포털 getLockUpRetuInfo_V3",
          "holder_name": null,
          "reason": null
        },
        {
          "period": "1개월",
          "date": "2026-04-27",
          "date_display": "2026-04-27",
          "tradable_date": "2026-04-27",
          "qty": 180123,
          "pct": 1.7,
          "type": "보호예수",
          "category": "구주·보호예수",
          "status": "반환확인_API수정",
          "source": "투자설명서",
          "source_label": "투자설명서 유통가능 요약표",
          "rcp": "20260313000893",
          "api_checked": true,
          "api_return_date": "2026-04-27",
          "api_return_qty": 180123,
          "api_source": "공공데이터포털 getLockUpRetuInfo_V3",
          "holder_name": "기관투자가",
          "reason": "기관투자가"
        },
        {
          "period": "2개월",
          "date": "2026-05-26",
          "date_display": "2026-05-26",
          "tradable_date": "2026-05-26",
          "qty": 80125,
          "pct": 0.76,
          "type": "보호예수",
          "category": "구주·보호예수",
          "status": "반환확인",
          "source": "투자설명서",
          "source_label": "투자설명서 유통가능 요약표",
          "rcp": "20260313000893",
          "api_checked": true,
          "api_return_date": "2026-05-26",
          "api_return_qty": 80125,
          "api_source": "공공데이터포털 getLockUpRetuInfo_V3",
          "holder_name": "벤처금융",
          "reason": "벤처금융"
        },
        {
          "period": "3개월",
          "date": "2026-06-25",
          "date_display": "2026-06-25",
          "tradable_date": "2026-06-25",
          "qty": 175096,
          "pct": 1.66,
          "type": "IPO확약",
          "category": "IPO기관",
          "status": "확정(경과)",
          "source": "DART",
          "source_label": "증권발행실적보고서",
          "rcp": "20260319000561",
          "api_checked": false,
          "api_return_date": null,
          "api_return_qty": null,
          "api_source": "공공데이터포털 getLockUpRetuInfo_V3",
          "holder_name": null,
          "reason": null
        },
        {
          "period": "3개월",
          "date": "2026-06-25",
          "date_display": "2026-06-25",
          "tradable_date": "2026-06-25",
          "qty": 6600,
          "pct": 0.06,
          "type": "보호예수",
          "category": "구주·보호예수",
          "status": "반환확인_API수정",
          "source": "투자설명서",
          "source_label": "투자설명서 유통가능 요약표",
          "rcp": "20260313000893",
          "api_checked": true,
          "api_return_date": "2026-06-25",
          "api_return_qty": 6600,
          "api_source": "공공데이터포털 getLockUpRetuInfo_V3",
          "holder_name": "상장주선인(국내기업)",
          "reason": "상장주선인(국내기업)"
        },
        {
          "period": "6개월",
          "date": "2026-09-25",
          "date_display": "2026-09-25",
          "tradable_date": "2026-09-25",
          "qty": 148051,
          "pct": 1.4,
          "type": "IPO확약",
          "category": "IPO기관",
          "status": "예정",
          "source": "DART",
          "source_label": "증권발행실적보고서",
          "rcp": "20260319000561",
          "api_checked": false,
          "api_return_date": null,
          "api_return_qty": null,
          "api_source": "공공데이터포털 getLockUpRetuInfo_V3",
          "holder_name": null,
          "reason": null
        },
        {
          "period": "6개월",
          "date": "2026-09-25",
          "date_display": "2026-09-25",
          "tradable_date": "2026-09-25",
          "qty": 876023,
          "pct": 8.29,
          "type": "보호예수",
          "category": "구주·보호예수",
          "status": "예정",
          "source": "투자설명서",
          "source_label": "투자설명서 유통가능 요약표",
          "rcp": "20260313000893",
          "api_checked": false,
          "api_return_date": null,
          "api_return_qty": null,
          "api_source": "공공데이터포털 getLockUpRetuInfo_V3",
          "holder_name": null,
          "reason": null
        },
        {
          "period": "2년",
          "date": "2028-03-25",
          "date_display": "2028-03-25",
          "tradable_date": "2028-03-25",
          "qty": 4720000,
          "pct": 44.65,
          "type": "보호예수",
          "category": "구주·보호예수",
          "status": "예정",
          "source": "투자설명서",
          "source_label": "투자설명서 유통가능 요약표",
          "rcp": "20260313000893",
          "api_checked": false,
          "api_return_date": null,
          "api_return_qty": null,
          "api_source": "공공데이터포털 getLockUpRetuInfo_V3",
          "holder_name": null,
          "reason": null
        }
      ],
      "holders": []
    },
    {
      "code": "0088M0",
      "name": "메쥬",
      "market": "코스닥",
      "listing_date": "2026-03-26",
      "shares": 9717750,
      "close_price": 39000,
      "events": [
        {
          "period": "15일",
          "date": "2026-04-10",
          "date_display": "2026-04-10",
          "tradable_date": "2026-04-10",
          "qty": 86567,
          "pct": 0.89,
          "type": "IPO확약",
          "category": "IPO기관",
          "status": "확정(경과)",
          "source": "DART",
          "source_label": "증권발행실적보고서",
          "rcp": "20260319000286",
          "api_checked": false,
          "api_return_date": null,
          "api_return_qty": null,
          "api_source": "공공데이터포털 getLockUpRetuInfo_V3",
          "holder_name": null,
          "reason": null
        },
        {
          "period": "1개월",
          "date": "2026-04-26",
          "date_display": "2026-04-26",
          "tradable_date": "2026-04-26",
          "qty": 110162,
          "pct": 1.13,
          "type": "IPO확약",
          "category": "IPO기관",
          "status": "확정(경과)",
          "source": "DART",
          "source_label": "증권발행실적보고서",
          "rcp": "20260319000286",
          "api_checked": false,
          "api_return_date": null,
          "api_return_qty": null,
          "api_source": "공공데이터포털 getLockUpRetuInfo_V3",
          "holder_name": null,
          "reason": null
        },
        {
          "period": "1개월",
          "date": "2026-04-27",
          "date_display": "2026-04-27",
          "tradable_date": "2026-04-27",
          "qty": 26000,
          "pct": 0.27,
          "type": "보호예수",
          "category": "구주·보호예수",
          "status": "반환확인_API수정",
          "source": "투자설명서",
          "source_label": "투자설명서 유통가능 요약표",
          "rcp": "20260313000316",
          "api_checked": true,
          "api_return_date": "2026-04-27",
          "api_return_qty": 26000,
          "api_source": "공공데이터포털 getLockUpRetuInfo_V3",
          "holder_name": "기타 보호예수 필요 주주",
          "reason": "기타 보호예수 필요 주주"
        },
        {
          "period": "2개월",
          "date": "2026-05-26",
          "date_display": "2026-05-26",
          "tradable_date": "2026-05-26",
          "qty": 96860,
          "pct": 1.0,
          "type": "보호예수",
          "category": "구주·보호예수",
          "status": "반환확인",
          "source": "투자설명서",
          "source_label": "투자설명서 유통가능 요약표",
          "rcp": "20260313000316",
          "api_checked": true,
          "api_return_date": "2026-05-26",
          "api_return_qty": 96860,
          "api_source": "공공데이터포털 getLockUpRetuInfo_V3",
          "holder_name": "기타 보호예수 필요 주주",
          "reason": "기타 보호예수 필요 주주"
        },
        {
          "period": "3개월",
          "date": "2026-06-26",
          "date_display": "2026-06-26",
          "tradable_date": "2026-06-26",
          "qty": 350633,
          "pct": 3.61,
          "type": "IPO확약",
          "category": "IPO기관",
          "status": "확정(경과)",
          "source": "DART",
          "source_label": "증권발행실적보고서",
          "rcp": "20260319000286",
          "api_checked": false,
          "api_return_date": null,
          "api_return_qty": null,
          "api_source": "공공데이터포털 getLockUpRetuInfo_V3",
          "holder_name": null,
          "reason": null
        },
        {
          "period": "3개월",
          "date": "2026-06-26",
          "date_display": "2026-06-26",
          "tradable_date": "2026-06-26",
          "qty": 20400,
          "pct": 0.21,
          "type": "보호예수",
          "category": "구주·보호예수",
          "status": "반환확인_API수정",
          "source": "투자설명서",
          "source_label": "투자설명서 유통가능 요약표",
          "rcp": "20260313000316",
          "api_checked": true,
          "api_return_date": "2026-06-26",
          "api_return_qty": 20400,
          "api_source": "공공데이터포털 getLockUpRetuInfo_V3",
          "holder_name": "기타 보호예수 필요 주주",
          "reason": "기타 보호예수 필요 주주"
        },
        {
          "period": "6개월",
          "date": "2026-09-26",
          "date_display": "2026-09-26",
          "tradable_date": "2026-09-26",
          "qty": 427670,
          "pct": 4.4,
          "type": "IPO확약",
          "category": "IPO기관",
          "status": "예정",
          "source": "DART",
          "source_label": "증권발행실적보고서",
          "rcp": "20260319000286",
          "api_checked": false,
          "api_return_date": null,
          "api_return_qty": null,
          "api_source": "공공데이터포털 getLockUpRetuInfo_V3",
          "holder_name": null,
          "reason": null
        },
        {
          "period": "1년",
          "date": "2027-03-26",
          "date_display": "2027-03-26",
          "tradable_date": "2027-03-26",
          "qty": 310000,
          "pct": 3.19,
          "type": "보호예수",
          "category": "구주·보호예수",
          "status": "예정",
          "source": "투자설명서",
          "source_label": "투자설명서 유통가능 요약표",
          "rcp": "20260313000316",
          "api_checked": false,
          "api_return_date": null,
          "api_return_qty": null,
          "api_source": "공공데이터포털 getLockUpRetuInfo_V3",
          "holder_name": null,
          "reason": null
        },
        {
          "period": "2년",
          "date": "2028-03-26",
          "date_display": "2028-03-26",
          "tradable_date": "2028-03-26",
          "qty": 370920,
          "pct": 3.82,
          "type": "보호예수",
          "category": "구주·보호예수",
          "status": "예정",
          "source": "투자설명서",
          "source_label": "투자설명서 유통가능 요약표",
          "rcp": "20260313000316",
          "api_checked": false,
          "api_return_date": null,
          "api_return_qty": null,
          "api_source": "공공데이터포털 getLockUpRetuInfo_V3",
          "holder_name": null,
          "reason": null
        },
        {
          "period": "3년",
          "date": "2029-03-26",
          "date_display": "2029-03-26",
          "tradable_date": "2029-03-26",
          "qty": 3573940,
          "pct": 36.78,
          "type": "보호예수",
          "category": "구주·보호예수",
          "status": "예정",
          "source": "투자설명서",
          "source_label": "투자설명서 유통가능 요약표",
          "rcp": "20260313000316",
          "api_checked": false,
          "api_return_date": null,
          "api_return_qty": null,
          "api_source": "공공데이터포털 getLockUpRetuInfo_V3",
          "holder_name": null,
          "reason": null
        }
      ],
      "holders": []
    },
    {
      "code": "394420",
      "name": "리센스메디컬",
      "market": "코스닥",
      "listing_date": "2026-03-31",
      "shares": 10850298,
      "close_price": 18450,
      "events": [
        {
          "period": "15일",
          "date": "2026-04-15",
          "date_display": "2026-04-15",
          "tradable_date": "2026-04-15",
          "qty": 227288,
          "pct": 2.09,
          "type": "IPO확약",
          "category": "IPO기관",
          "status": "확정(경과)",
          "source": "DART",
          "source_label": "증권발행실적보고서",
          "rcp": "20260324000387",
          "api_checked": false,
          "api_return_date": null,
          "api_return_qty": null,
          "api_source": "공공데이터포털 getLockUpRetuInfo_V3",
          "holder_name": null,
          "reason": null
        },
        {
          "period": "1개월",
          "date": "2026-04-30",
          "date_display": "2026-04-30",
          "tradable_date": "2026-04-30",
          "qty": 190808,
          "pct": 1.76,
          "type": "IPO확약",
          "category": "IPO기관",
          "status": "확정(경과)",
          "source": "DART",
          "source_label": "증권발행실적보고서",
          "rcp": "20260324000387",
          "api_checked": false,
          "api_return_date": null,
          "api_return_qty": null,
          "api_source": "공공데이터포털 getLockUpRetuInfo_V3",
          "holder_name": null,
          "reason": null
        },
        {
          "period": "1개월",
          "date": "2026-04-30",
          "date_display": "2026-04-30",
          "tradable_date": "2026-04-30",
          "qty": 2251518,
          "pct": 20.75,
          "type": "보호예수",
          "category": "구주·보호예수",
          "status": "확정(경과)",
          "source": "투자설명서",
          "source_label": "투자설명서 유통가능 요약표",
          "rcp": "20260318000042",
          "api_checked": false,
          "api_return_date": null,
          "api_return_qty": null,
          "api_source": "공공데이터포털 getLockUpRetuInfo_V3",
          "holder_name": null,
          "reason": null
        },
        {
          "period": "보호예수",
          "date": "2026-05-04",
          "date_display": "2026-05-04",
          "tradable_date": "2026-05-04",
          "qty": 1458791,
          "pct": 13.44,
          "type": "보호예수",
          "category": "구주·보호예수",
          "status": "반환확인_API수정",
          "source": "투자설명서",
          "source_label": "공공데이터 API 단독",
          "rcp": "",
          "api_checked": true,
          "api_return_date": "2026-05-04",
          "api_return_qty": 1458791,
          "api_source": "공공데이터포털 getLockUpRetuInfo_V3",
          "holder_name": "기타 보호예수 필요 주주",
          "reason": "기타 보호예수 필요 주주"
        },
        {
          "period": "2개월",
          "date": "2026-06-01",
          "date_display": "2026-06-01",
          "tradable_date": "2026-06-01",
          "qty": 972528,
          "pct": 8.96,
          "type": "보호예수",
          "category": "구주·보호예수",
          "status": "반환확인_API수정",
          "source": "투자설명서",
          "source_label": "투자설명서 유통가능 요약표",
          "rcp": "20260318000042",
          "api_checked": true,
          "api_return_date": "2026-06-01",
          "api_return_qty": 972528,
          "api_source": "공공데이터포털 getLockUpRetuInfo_V3",
          "holder_name": "기타 보호예수 필요 주주",
          "reason": "기타 보호예수 필요 주주"
        },
        {
          "period": "3개월",
          "date": "2026-06-30",
          "date_display": "2026-06-30",
          "tradable_date": "2026-06-30",
          "qty": 319192,
          "pct": 2.94,
          "type": "IPO확약",
          "category": "IPO기관",
          "status": "확정(경과)",
          "source": "DART",
          "source_label": "증권발행실적보고서",
          "rcp": "20260324000387",
          "api_checked": false,
          "api_return_date": null,
          "api_return_qty": null,
          "api_source": "공공데이터포털 getLockUpRetuInfo_V3",
          "holder_name": null,
          "reason": null
        },
        {
          "period": "3개월",
          "date": "2026-06-30",
          "date_display": "2026-06-30",
          "tradable_date": "2026-06-30",
          "qty": 1246456,
          "pct": 11.49,
          "type": "보호예수",
          "category": "구주·보호예수",
          "status": "확정(경과)",
          "source": "투자설명서",
          "source_label": "투자설명서 유통가능 요약표",
          "rcp": "20260318000042",
          "api_checked": false,
          "api_return_date": null,
          "api_return_qty": null,
          "api_source": "공공데이터포털 getLockUpRetuInfo_V3",
          "holder_name": null,
          "reason": null
        },
        {
          "period": "보호예수",
          "date": "2026-07-01",
          "date_display": "2026-07-01",
          "tradable_date": "2026-07-01",
          "qty": 1040366,
          "pct": 9.59,
          "type": "보호예수",
          "category": "구주·보호예수",
          "status": "반환확인_API수정",
          "source": "투자설명서",
          "source_label": "공공데이터 API 단독",
          "rcp": "",
          "api_checked": true,
          "api_return_date": "2026-07-01",
          "api_return_qty": 1040366,
          "api_source": "공공데이터포털 getLockUpRetuInfo_V3",
          "holder_name": "기타 보호예수 필요 주주",
          "reason": "기타 보호예수 필요 주주"
        },
        {
          "period": "6개월",
          "date": "2026-09-30",
          "date_display": "2026-09-30",
          "tradable_date": "2026-09-30",
          "qty": 251365,
          "pct": 2.32,
          "type": "IPO확약",
          "category": "IPO기관",
          "status": "예정",
          "source": "DART",
          "source_label": "증권발행실적보고서",
          "rcp": "20260324000387",
          "api_checked": false,
          "api_return_date": null,
          "api_return_qty": null,
          "api_source": "공공데이터포털 getLockUpRetuInfo_V3",
          "holder_name": null,
          "reason": null
        },
        {
          "period": "6개월",
          "date": "2026-09-30",
          "date_display": "2026-09-30",
          "tradable_date": "2026-09-30",
          "qty": 78629,
          "pct": 0.72,
          "type": "보호예수",
          "category": "구주·보호예수",
          "status": "예정",
          "source": "투자설명서",
          "source_label": "투자설명서 유통가능 요약표",
          "rcp": "20260318000042",
          "api_checked": false,
          "api_return_date": null,
          "api_return_qty": null,
          "api_source": "공공데이터포털 getLockUpRetuInfo_V3",
          "holder_name": null,
          "reason": null
        },
        {
          "period": "1년",
          "date": "2027-03-31",
          "date_display": "2027-03-31",
          "tradable_date": "2027-03-31",
          "qty": 418432,
          "pct": 3.86,
          "type": "보호예수",
          "category": "구주·보호예수",
          "status": "예정",
          "source": "투자설명서",
          "source_label": "투자설명서 유통가능 요약표",
          "rcp": "20260318000042",
          "api_checked": false,
          "api_return_date": null,
          "api_return_qty": null,
          "api_source": "공공데이터포털 getLockUpRetuInfo_V3",
          "holder_name": null,
          "reason": null
        },
        {
          "period": "5년",
          "date": "2031-03-31",
          "date_display": "2031-03-31",
          "tradable_date": "2031-03-31",
          "qty": 2170059,
          "pct": 20.0,
          "type": "보호예수",
          "category": "구주·보호예수",
          "status": "예정",
          "source": "투자설명서",
          "source_label": "투자설명서 유통가능 요약표",
          "rcp": "20260318000042",
          "api_checked": false,
          "api_return_date": null,
          "api_return_qty": null,
          "api_source": "공공데이터포털 getLockUpRetuInfo_V3",
          "holder_name": null,
          "reason": null
        }
      ],
      "holders": []
    },
    {
      "code": "0007J0",
      "name": "인벤테라",
      "market": "코스닥",
      "listing_date": "2026-04-02",
      "shares": 7865714,
      "close_price": 35250,
      "events": [
        {
          "period": "15일",
          "date": "2026-04-17",
          "date_display": "2026-04-17",
          "tradable_date": "2026-04-17",
          "qty": 271000,
          "pct": 3.45,
          "type": "IPO확약",
          "category": "IPO기관",
          "status": "확정(경과)",
          "source": "DART",
          "source_label": "증권발행실적보고서",
          "rcp": "20260326001120",
          "api_checked": false,
          "api_return_date": null,
          "api_return_qty": null,
          "api_source": "공공데이터포털 getLockUpRetuInfo_V3",
          "holder_name": null,
          "reason": null
        },
        {
          "period": "1개월",
          "date": "2026-05-04",
          "date_display": "2026-05-04",
          "tradable_date": "2026-05-04",
          "qty": 362798,
          "pct": 4.61,
          "type": "IPO확약",
          "category": "IPO기관",
          "status": "반환확인_API수정",
          "source": "DART",
          "source_label": "증권발행실적보고서",
          "rcp": "20260326001120",
          "api_checked": true,
          "api_return_date": "2026-05-04",
          "api_return_qty": 362798,
          "api_source": "공공데이터포털 getLockUpRetuInfo_V3",
          "holder_name": "기타 보호예수 필요 주주",
          "reason": "기타 보호예수 필요 주주"
        },
        {
          "period": "보호예수",
          "date": "2026-06-02",
          "date_display": "2026-06-02",
          "tradable_date": "2026-06-02",
          "qty": 362795,
          "pct": 4.61,
          "type": "보호예수",
          "category": "구주·보호예수",
          "status": "반환확인_API수정",
          "source": "투자설명서",
          "source_label": "공공데이터 API 단독",
          "rcp": "",
          "api_checked": true,
          "api_return_date": "2026-06-02",
          "api_return_qty": 362795,
          "api_source": "공공데이터포털 getLockUpRetuInfo_V3",
          "holder_name": "기타 보호예수 필요 주주",
          "reason": "기타 보호예수 필요 주주"
        },
        {
          "period": "3개월",
          "date": "2026-07-02",
          "date_display": "2026-07-02",
          "tradable_date": "2026-07-02",
          "qty": 35400,
          "pct": 0.45,
          "type": "IPO확약",
          "category": "IPO기관",
          "status": "반환확인_API수정",
          "source": "DART",
          "source_label": "증권발행실적보고서",
          "rcp": "20260326001120",
          "api_checked": true,
          "api_return_date": "2026-07-02",
          "api_return_qty": 35400,
          "api_source": "공공데이터포털 getLockUpRetuInfo_V3",
          "holder_name": "상장주선인(국내기업)",
          "reason": "상장주선인(국내기업)"
        },
        {
          "period": "6개월",
          "date": "2026-10-02",
          "date_display": "2026-10-02",
          "tradable_date": "2026-10-02",
          "qty": 219430,
          "pct": 2.79,
          "type": "IPO확약",
          "category": "IPO기관",
          "status": "예정",
          "source": "DART",
          "source_label": "증권발행실적보고서",
          "rcp": "20260326001120",
          "api_checked": false,
          "api_return_date": null,
          "api_return_qty": null,
          "api_source": "공공데이터포털 getLockUpRetuInfo_V3",
          "holder_name": null,
          "reason": null
        }
      ],
      "holders": []
    },
    {
      "code": "0011T0",
      "name": "채비",
      "market": "코스닥",
      "listing_date": "2026-04-29",
      "shares": 46785280,
      "close_price": 22550,
      "events": [
        {
          "period": "15일",
          "date": "2026-05-14",
          "date_display": "2026-05-14",
          "tradable_date": "2026-05-14",
          "qty": 9377,
          "pct": 0.02,
          "type": "IPO확약",
          "category": "IPO기관",
          "status": "확정(경과)",
          "source": "DART",
          "source_label": "증권발행실적보고서",
          "rcp": "20260423000734",
          "api_checked": false,
          "api_return_date": null,
          "api_return_qty": null,
          "api_source": "공공데이터포털 getLockUpRetuInfo_V3",
          "holder_name": null,
          "reason": null
        },
        {
          "period": "1개월",
          "date": "2026-05-29",
          "date_display": "2026-05-29",
          "tradable_date": "2026-05-29",
          "qty": 8028,
          "pct": 0.02,
          "type": "IPO확약",
          "category": "IPO기관",
          "status": "확정(경과)",
          "source": "DART",
          "source_label": "증권발행실적보고서",
          "rcp": "20260423000734",
          "api_checked": false,
          "api_return_date": null,
          "api_return_qty": null,
          "api_source": "공공데이터포털 getLockUpRetuInfo_V3",
          "holder_name": null,
          "reason": null
        },
        {
          "period": "1개월",
          "date": "2026-05-29",
          "date_display": "2026-05-29",
          "tradable_date": "2026-05-29",
          "qty": 2194110,
          "pct": 4.69,
          "type": "보호예수",
          "category": "구주·보호예수",
          "status": "반환확인",
          "source": "투자설명서",
          "source_label": "투자설명서 유통가능 요약표",
          "rcp": "20260417000497",
          "api_checked": true,
          "api_return_date": "2026-05-29",
          "api_return_qty": 2194110,
          "api_source": "공공데이터포털 getLockUpRetuInfo_V3",
          "holder_name": "벤처금융",
          "reason": "벤처금융"
        },
        {
          "period": "3개월",
          "date": "2026-07-29",
          "date_display": "2026-07-29",
          "tradable_date": "2026-07-29",
          "qty": 28388,
          "pct": 0.06,
          "type": "IPO확약",
          "category": "IPO기관",
          "status": "예정",
          "source": "DART",
          "source_label": "증권발행실적보고서",
          "rcp": "20260423000734",
          "api_checked": false,
          "api_return_date": null,
          "api_return_qty": null,
          "api_source": "공공데이터포털 getLockUpRetuInfo_V3",
          "holder_name": null,
          "reason": null
        },
        {
          "period": "6개월",
          "date": "2026-10-29",
          "date_display": "2026-10-29",
          "tradable_date": "2026-10-29",
          "qty": 960250,
          "pct": 2.05,
          "type": "IPO확약",
          "category": "IPO기관",
          "status": "예정",
          "source": "DART",
          "source_label": "증권발행실적보고서",
          "rcp": "20260423000734",
          "api_checked": false,
          "api_return_date": null,
          "api_return_qty": null,
          "api_source": "공공데이터포털 getLockUpRetuInfo_V3",
          "holder_name": null,
          "reason": null
        },
        {
          "period": "6개월",
          "date": "2026-10-29",
          "date_display": "2026-10-29",
          "tradable_date": "2026-10-29",
          "qty": 15313800,
          "pct": 32.73,
          "type": "보호예수",
          "category": "구주·보호예수",
          "status": "예정",
          "source": "투자설명서",
          "source_label": "투자설명서 유통가능 요약표",
          "rcp": "20260417000497",
          "api_checked": false,
          "api_return_date": null,
          "api_return_qty": null,
          "api_source": "공공데이터포털 getLockUpRetuInfo_V3",
          "holder_name": null,
          "reason": "마지막 누적 유통가능 주식수가 KRX 상장주식수와 불일치"
        },
        {
          "period": "1년",
          "date": "2027-04-29",
          "date_display": "2027-04-29",
          "tradable_date": "2027-04-29",
          "qty": 81300,
          "pct": 0.17,
          "type": "보호예수",
          "category": "구주·보호예수",
          "status": "예정",
          "source": "투자설명서",
          "source_label": "투자설명서 유통가능 요약표",
          "rcp": "20260417000497",
          "api_checked": false,
          "api_return_date": null,
          "api_return_qty": null,
          "api_source": "공공데이터포털 getLockUpRetuInfo_V3",
          "holder_name": null,
          "reason": "마지막 누적 유통가능 주식수가 KRX 상장주식수와 불일치"
        }
      ],
      "holders": []
    },
    {
      "code": "439960",
      "name": "코스모로보틱스",
      "market": "코스닥",
      "listing_date": "2026-05-11",
      "shares": 32108906,
      "close_price": 24000,
      "events": [
        {
          "period": "15일",
          "date": "2026-05-26",
          "date_display": "2026-05-26",
          "tradable_date": "2026-05-26",
          "qty": 300808,
          "pct": 0.94,
          "type": "IPO확약",
          "category": "IPO기관",
          "status": "확정(경과)",
          "source": "DART",
          "source_label": "증권발행실적보고서",
          "rcp": "20260430001330",
          "api_checked": false,
          "api_return_date": null,
          "api_return_qty": null,
          "api_source": "공공데이터포털 getLockUpRetuInfo_V3",
          "holder_name": null,
          "reason": null
        },
        {
          "period": "1개월",
          "date": "2026-06-11",
          "date_display": "2026-06-11",
          "tradable_date": "2026-06-11",
          "qty": 355781,
          "pct": 1.11,
          "type": "IPO확약",
          "category": "IPO기관",
          "status": "확정(경과)",
          "source": "DART",
          "source_label": "증권발행실적보고서",
          "rcp": "20260430001330",
          "api_checked": false,
          "api_return_date": null,
          "api_return_qty": null,
          "api_source": "공공데이터포털 getLockUpRetuInfo_V3",
          "holder_name": null,
          "reason": null
        },
        {
          "period": "1개월",
          "date": "2026-06-11",
          "date_display": "2026-06-11",
          "tradable_date": "2026-06-11",
          "qty": 3486536,
          "pct": 10.86,
          "type": "보호예수",
          "category": "구주·보호예수",
          "status": "반환확인",
          "source": "투자설명서",
          "source_label": "투자설명서 유통가능 요약표",
          "rcp": "20260424000530",
          "api_checked": true,
          "api_return_date": "2026-06-11",
          "api_return_qty": 3486536,
          "api_source": "공공데이터포털 getLockUpRetuInfo_V3",
          "holder_name": "기타 보호예수 필요 주주",
          "reason": "기타 보호예수 필요 주주"
        },
        {
          "period": "2개월",
          "date": "2026-07-13",
          "date_display": "2026-07-13",
          "tradable_date": "2026-07-13",
          "qty": 3210890,
          "pct": 10.0,
          "type": "보호예수",
          "category": "구주·보호예수",
          "status": "예정",
          "source": "투자설명서",
          "source_label": "투자설명서 유통가능 요약표",
          "rcp": "20260424000530",
          "api_checked": false,
          "api_return_date": null,
          "api_return_qty": null,
          "api_source": "공공데이터포털 getLockUpRetuInfo_V3",
          "holder_name": null,
          "reason": null
        },
        {
          "period": "3개월",
          "date": "2026-08-11",
          "date_display": "2026-08-11",
          "tradable_date": "2026-08-11",
          "qty": 1362502,
          "pct": 4.24,
          "type": "IPO확약",
          "category": "IPO기관",
          "status": "예정",
          "source": "DART",
          "source_label": "증권발행실적보고서",
          "rcp": "20260430001330",
          "api_checked": false,
          "api_return_date": null,
          "api_return_qty": null,
          "api_source": "공공데이터포털 getLockUpRetuInfo_V3",
          "holder_name": null,
          "reason": null
        },
        {
          "period": "3개월",
          "date": "2026-08-11",
          "date_display": "2026-08-11",
          "tradable_date": "2026-08-11",
          "qty": 430431,
          "pct": 1.34,
          "type": "보호예수",
          "category": "구주·보호예수",
          "status": "예정",
          "source": "투자설명서",
          "source_label": "투자설명서 유통가능 요약표",
          "rcp": "20260424000530",
          "api_checked": false,
          "api_return_date": null,
          "api_return_qty": null,
          "api_source": "공공데이터포털 getLockUpRetuInfo_V3",
          "holder_name": null,
          "reason": null
        },
        {
          "period": "6개월",
          "date": "2026-11-11",
          "date_display": "2026-11-11",
          "tradable_date": "2026-11-11",
          "qty": 818201,
          "pct": 2.55,
          "type": "IPO확약",
          "category": "IPO기관",
          "status": "예정",
          "source": "DART",
          "source_label": "증권발행실적보고서",
          "rcp": "20260430001330",
          "api_checked": false,
          "api_return_date": null,
          "api_return_qty": null,
          "api_source": "공공데이터포털 getLockUpRetuInfo_V3",
          "holder_name": null,
          "reason": null
        },
        {
          "period": "1년",
          "date": "2027-05-11",
          "date_display": "2027-05-11",
          "tradable_date": "2027-05-11",
          "qty": 2586098,
          "pct": 8.05,
          "type": "보호예수",
          "category": "구주·보호예수",
          "status": "예정",
          "source": "투자설명서",
          "source_label": "투자설명서 유통가능 요약표",
          "rcp": "20260424000530",
          "api_checked": false,
          "api_return_date": null,
          "api_return_qty": null,
          "api_source": "공공데이터포털 getLockUpRetuInfo_V3",
          "holder_name": null,
          "reason": null
        },
        {
          "period": "3년",
          "date": "2029-05-11",
          "date_display": "2029-05-11",
          "tradable_date": "2029-05-11",
          "qty": 12100947,
          "pct": 37.69,
          "type": "보호예수",
          "category": "구주·보호예수",
          "status": "예정",
          "source": "투자설명서",
          "source_label": "투자설명서 유통가능 요약표",
          "rcp": "20260424000530",
          "api_checked": false,
          "api_return_date": null,
          "api_return_qty": null,
          "api_source": "공공데이터포털 getLockUpRetuInfo_V3",
          "holder_name": null,
          "reason": null
        }
      ],
      "holders": []
    },
    {
      "code": "487580",
      "name": "폴레드",
      "market": "코스닥",
      "listing_date": "2026-05-14",
      "shares": 25182861,
      "close_price": 20000,
      "events": [
        {
          "period": "15일",
          "date": "2026-05-29",
          "date_display": "2026-05-29",
          "tradable_date": "2026-05-29",
          "qty": 522510,
          "pct": 2.07,
          "type": "IPO확약",
          "category": "IPO기관",
          "status": "확정(경과)",
          "source": "DART",
          "source_label": "증권발행실적보고서",
          "rcp": "20260508000515",
          "api_checked": false,
          "api_return_date": null,
          "api_return_qty": null,
          "api_source": "공공데이터포털 getLockUpRetuInfo_V3",
          "holder_name": null,
          "reason": null
        },
        {
          "period": "1개월",
          "date": "2026-06-14",
          "date_display": "2026-06-14",
          "tradable_date": "2026-06-14",
          "qty": 394770,
          "pct": 1.57,
          "type": "IPO확약",
          "category": "IPO기관",
          "status": "확정(경과)",
          "source": "DART",
          "source_label": "증권발행실적보고서",
          "rcp": "20260508000515",
          "api_checked": false,
          "api_return_date": null,
          "api_return_qty": null,
          "api_source": "공공데이터포털 getLockUpRetuInfo_V3",
          "holder_name": null,
          "reason": null
        },
        {
          "period": "1개월",
          "date": "2026-06-15",
          "date_display": "2026-06-15",
          "tradable_date": "2026-06-15",
          "qty": 2462316,
          "pct": 9.78,
          "type": "보호예수",
          "category": "구주·보호예수",
          "status": "반환확인_API수정",
          "source": "투자설명서",
          "source_label": "투자설명서 유통가능 요약표",
          "rcp": "20260430000415",
          "api_checked": true,
          "api_return_date": "2026-06-15",
          "api_return_qty": 2462316,
          "api_source": "공공데이터포털 getLockUpRetuInfo_V3",
          "holder_name": "기타 보호예수 필요 주주",
          "reason": "기타 보호예수 필요 주주"
        },
        {
          "period": "2개월",
          "date": "2026-07-14",
          "date_display": "2026-07-14",
          "tradable_date": "2026-07-14",
          "qty": 3345505,
          "pct": 13.28,
          "type": "보호예수",
          "category": "구주·보호예수",
          "status": "예정",
          "source": "투자설명서",
          "source_label": "투자설명서 유통가능 요약표",
          "rcp": "20260430000415",
          "api_checked": false,
          "api_return_date": null,
          "api_return_qty": null,
          "api_source": "공공데이터포털 getLockUpRetuInfo_V3",
          "holder_name": null,
          "reason": null
        },
        {
          "period": "3개월",
          "date": "2026-08-14",
          "date_display": "2026-08-14",
          "tradable_date": "2026-08-14",
          "qty": 503650,
          "pct": 2.0,
          "type": "IPO확약",
          "category": "IPO기관",
          "status": "예정",
          "source": "DART",
          "source_label": "증권발행실적보고서",
          "rcp": "20260508000515",
          "api_checked": false,
          "api_return_date": null,
          "api_return_qty": null,
          "api_source": "공공데이터포털 getLockUpRetuInfo_V3",
          "holder_name": null,
          "reason": null
        },
        {
          "period": "3개월",
          "date": "2026-08-14",
          "date_display": "2026-08-14",
          "tradable_date": "2026-08-14",
          "qty": 4293433,
          "pct": 17.05,
          "type": "보호예수",
          "category": "구주·보호예수",
          "status": "예정",
          "source": "투자설명서",
          "source_label": "투자설명서 유통가능 요약표",
          "rcp": "20260430000415",
          "api_checked": false,
          "api_return_date": null,
          "api_return_qty": null,
          "api_source": "공공데이터포털 getLockUpRetuInfo_V3",
          "holder_name": null,
          "reason": null
        },
        {
          "period": "6개월",
          "date": "2026-11-14",
          "date_display": "2026-11-14",
          "tradable_date": "2026-11-14",
          "qty": 258500,
          "pct": 1.03,
          "type": "IPO확약",
          "category": "IPO기관",
          "status": "예정",
          "source": "DART",
          "source_label": "증권발행실적보고서",
          "rcp": "20260508000515",
          "api_checked": false,
          "api_return_date": null,
          "api_return_qty": null,
          "api_source": "공공데이터포털 getLockUpRetuInfo_V3",
          "holder_name": null,
          "reason": null
        },
        {
          "period": "6개월",
          "date": "2026-11-14",
          "date_display": "2026-11-14",
          "tradable_date": "2026-11-14",
          "qty": 225000,
          "pct": 0.89,
          "type": "보호예수",
          "category": "구주·보호예수",
          "status": "예정",
          "source": "투자설명서",
          "source_label": "투자설명서 유통가능 요약표",
          "rcp": "20260430000415",
          "api_checked": false,
          "api_return_date": null,
          "api_return_qty": null,
          "api_source": "공공데이터포털 getLockUpRetuInfo_V3",
          "holder_name": null,
          "reason": null
        },
        {
          "period": "30개월",
          "date": "2028-11-14",
          "date_display": "2028-11-14",
          "tradable_date": "2028-11-14",
          "qty": 7064280,
          "pct": 28.05,
          "type": "보호예수",
          "category": "구주·보호예수",
          "status": "예정",
          "source": "투자설명서",
          "source_label": "투자설명서 유통가능 요약표",
          "rcp": "20260430000415",
          "api_checked": false,
          "api_return_date": null,
          "api_return_qty": null,
          "api_source": "공공데이터포털 getLockUpRetuInfo_V3",
          "holder_name": null,
          "reason": null
        }
      ],
      "holders": []
    },
    {
      "code": "477850",
      "name": "마키나락스",
      "market": "코스닥",
      "listing_date": "2026-05-20",
      "shares": 17541640,
      "close_price": 60000,
      "events": [
        {
          "period": "15일",
          "date": "2026-06-04",
          "date_display": "2026-06-04",
          "tradable_date": "2026-06-04",
          "qty": 83150,
          "pct": 0.47,
          "type": "IPO확약",
          "category": "IPO기관",
          "status": "확정(경과)",
          "source": "DART",
          "source_label": "증권발행실적보고서",
          "rcp": "20260514001096",
          "api_checked": false,
          "api_return_date": null,
          "api_return_qty": null,
          "api_source": "공공데이터포털 getLockUpRetuInfo_V3",
          "holder_name": null,
          "reason": null
        },
        {
          "period": "1개월",
          "date": "2026-06-20",
          "date_display": "2026-06-20",
          "tradable_date": "2026-06-20",
          "qty": 151465,
          "pct": 0.86,
          "type": "IPO확약",
          "category": "IPO기관",
          "status": "확정(경과)",
          "source": "DART",
          "source_label": "증권발행실적보고서",
          "rcp": "20260514001096",
          "api_checked": false,
          "api_return_date": null,
          "api_return_qty": null,
          "api_source": "공공데이터포털 getLockUpRetuInfo_V3",
          "holder_name": null,
          "reason": null
        },
        {
          "period": "1개월",
          "date": "2026-06-22",
          "date_display": "2026-06-22",
          "tradable_date": "2026-06-22",
          "qty": 332459,
          "pct": 1.9,
          "type": "보호예수",
          "category": "구주·보호예수",
          "status": "반환확인_API수정",
          "source": "투자설명서",
          "source_label": "투자설명서 유통가능 요약표",
          "rcp": "20260508000924",
          "api_checked": true,
          "api_return_date": "2026-06-22",
          "api_return_qty": 332459,
          "api_source": "공공데이터포털 getLockUpRetuInfo_V3",
          "holder_name": "기타 보호예수 필요 주주",
          "reason": "기타 보호예수 필요 주주"
        },
        {
          "period": "2개월",
          "date": "2026-07-20",
          "date_display": "2026-07-20",
          "tradable_date": "2026-07-20",
          "qty": 1995141,
          "pct": 11.37,
          "type": "보호예수",
          "category": "구주·보호예수",
          "status": "예정",
          "source": "투자설명서",
          "source_label": "투자설명서 유통가능 요약표",
          "rcp": "20260508000924",
          "api_checked": false,
          "api_return_date": null,
          "api_return_qty": null,
          "api_source": "공공데이터포털 getLockUpRetuInfo_V3",
          "holder_name": null,
          "reason": null
        },
        {
          "period": "3개월",
          "date": "2026-08-20",
          "date_display": "2026-08-20",
          "tradable_date": "2026-08-20",
          "qty": 520076,
          "pct": 2.96,
          "type": "IPO확약",
          "category": "IPO기관",
          "status": "예정",
          "source": "DART",
          "source_label": "증권발행실적보고서",
          "rcp": "20260514001096",
          "api_checked": false,
          "api_return_date": null,
          "api_return_qty": null,
          "api_source": "공공데이터포털 getLockUpRetuInfo_V3",
          "holder_name": null,
          "reason": null
        },
        {
          "period": "3개월",
          "date": "2026-08-20",
          "date_display": "2026-08-20",
          "tradable_date": "2026-08-20",
          "qty": 399124,
          "pct": 2.28,
          "type": "보호예수",
          "category": "구주·보호예수",
          "status": "예정",
          "source": "투자설명서",
          "source_label": "투자설명서 유통가능 요약표",
          "rcp": "20260508000924",
          "api_checked": false,
          "api_return_date": null,
          "api_return_qty": null,
          "api_source": "공공데이터포털 getLockUpRetuInfo_V3",
          "holder_name": null,
          "reason": null
        },
        {
          "period": "6개월",
          "date": "2026-11-20",
          "date_display": "2026-11-20",
          "tradable_date": "2026-11-20",
          "qty": 842820,
          "pct": 4.8,
          "type": "IPO확약",
          "category": "IPO기관",
          "status": "예정",
          "source": "DART",
          "source_label": "증권발행실적보고서",
          "rcp": "20260514001096",
          "api_checked": false,
          "api_return_date": null,
          "api_return_qty": null,
          "api_source": "공공데이터포털 getLockUpRetuInfo_V3",
          "holder_name": null,
          "reason": null
        },
        {
          "period": "6개월",
          "date": "2026-11-20",
          "date_display": "2026-11-20",
          "tradable_date": "2026-11-20",
          "qty": 1824949,
          "pct": 10.4,
          "type": "보호예수",
          "category": "구주·보호예수",
          "status": "예정",
          "source": "투자설명서",
          "source_label": "투자설명서 유통가능 요약표",
          "rcp": "20260508000924",
          "api_checked": false,
          "api_return_date": null,
          "api_return_qty": null,
          "api_source": "공공데이터포털 getLockUpRetuInfo_V3",
          "holder_name": null,
          "reason": null
        },
        {
          "period": "1년",
          "date": "2027-05-20",
          "date_display": "2027-05-20",
          "tradable_date": "2027-05-20",
          "qty": 636104,
          "pct": 3.63,
          "type": "보호예수",
          "category": "구주·보호예수",
          "status": "예정",
          "source": "투자설명서",
          "source_label": "투자설명서 유통가능 요약표",
          "rcp": "20260508000924",
          "api_checked": false,
          "api_return_date": null,
          "api_return_qty": null,
          "api_source": "공공데이터포털 getLockUpRetuInfo_V3",
          "holder_name": null,
          "reason": null
        },
        {
          "period": "3년",
          "date": "2029-05-20",
          "date_display": "2029-05-20",
          "tradable_date": "2029-05-20",
          "qty": 5477016,
          "pct": 31.22,
          "type": "보호예수",
          "category": "구주·보호예수",
          "status": "예정",
          "source": "투자설명서",
          "source_label": "투자설명서 유통가능 요약표",
          "rcp": "20260508000924",
          "api_checked": false,
          "api_return_date": null,
          "api_return_qty": null,
          "api_source": "공공데이터포털 getLockUpRetuInfo_V3",
          "holder_name": null,
          "reason": null
        }
      ],
      "holders": []
    },
    {
      "code": "0117P0",
      "name": "피스피스스튜디오",
      "market": "코스닥",
      "listing_date": "2026-06-08",
      "shares": 14168911,
      "close_price": 13730,
      "events": [
        {
          "period": "15일",
          "date": "2026-06-23",
          "date_display": "2026-06-23",
          "tradable_date": "2026-06-23",
          "qty": 780642,
          "pct": 5.51,
          "type": "IPO확약",
          "category": "IPO기관",
          "status": "확정(경과)",
          "source": "DART",
          "source_label": "증권발행실적보고서",
          "rcp": "20260529001298",
          "api_checked": false,
          "api_return_date": null,
          "api_return_qty": null,
          "api_source": "공공데이터포털 getLockUpRetuInfo_V3",
          "holder_name": null,
          "reason": null
        },
        {
          "period": "1개월",
          "date": "2026-07-08",
          "date_display": "2026-07-08",
          "tradable_date": "2026-07-08",
          "qty": 191880,
          "pct": 1.35,
          "type": "IPO확약",
          "category": "IPO기관",
          "status": "예정",
          "source": "DART",
          "source_label": "증권발행실적보고서",
          "rcp": "20260529001298",
          "api_checked": false,
          "api_return_date": null,
          "api_return_qty": null,
          "api_source": "공공데이터포털 getLockUpRetuInfo_V3",
          "holder_name": null,
          "reason": null
        },
        {
          "period": "3개월",
          "date": "2026-09-08",
          "date_display": "2026-09-08",
          "tradable_date": "2026-09-08",
          "qty": 3580,
          "pct": 0.03,
          "type": "IPO확약",
          "category": "IPO기관",
          "status": "예정",
          "source": "DART",
          "source_label": "증권발행실적보고서",
          "rcp": "20260529001298",
          "api_checked": false,
          "api_return_date": null,
          "api_return_qty": null,
          "api_source": "공공데이터포털 getLockUpRetuInfo_V3",
          "holder_name": null,
          "reason": null
        },
        {
          "period": "6개월",
          "date": "2026-12-08",
          "date_display": "2026-12-08",
          "tradable_date": "2026-12-08",
          "qty": 294512,
          "pct": 2.08,
          "type": "IPO확약",
          "category": "IPO기관",
          "status": "예정",
          "source": "DART",
          "source_label": "증권발행실적보고서",
          "rcp": "20260529001298",
          "api_checked": false,
          "api_return_date": null,
          "api_return_qty": null,
          "api_source": "공공데이터포털 getLockUpRetuInfo_V3",
          "holder_name": null,
          "reason": null
        }
      ],
      "holders": []
    },
    {
      "code": "153890",
      "name": "져스텍",
      "market": "코스닥",
      "listing_date": "2026-06-29",
      "shares": 12050305,
      "close_price": 17530,
      "events": [
        {
          "period": "15일",
          "date": "2026-07-14",
          "date_display": "2026-07-14",
          "tradable_date": "2026-07-14",
          "qty": 181110,
          "pct": 1.5,
          "type": "IPO확약",
          "category": "IPO기관",
          "status": "예정",
          "source": "DART",
          "source_label": "증권발행실적보고서",
          "rcp": "20260623000136",
          "api_checked": false,
          "api_return_date": null,
          "api_return_qty": null,
          "api_source": "공공데이터포털 getLockUpRetuInfo_V3",
          "holder_name": null,
          "reason": null
        },
        {
          "period": "1개월",
          "date": "2026-07-29",
          "date_display": "2026-07-29",
          "tradable_date": "2026-07-29",
          "qty": 186357,
          "pct": 1.55,
          "type": "IPO확약",
          "category": "IPO기관",
          "status": "예정",
          "source": "DART",
          "source_label": "증권발행실적보고서",
          "rcp": "20260623000136",
          "api_checked": false,
          "api_return_date": null,
          "api_return_qty": null,
          "api_source": "공공데이터포털 getLockUpRetuInfo_V3",
          "holder_name": null,
          "reason": null
        },
        {
          "period": "1개월",
          "date": "2026-07-29",
          "date_display": "2026-07-29",
          "tradable_date": "2026-07-29",
          "qty": 1513980,
          "pct": 12.56,
          "type": "보호예수",
          "category": "구주·보호예수",
          "status": "예정",
          "source": "투자설명서",
          "source_label": "투자설명서 유통가능 요약표",
          "rcp": "20260616000250",
          "api_checked": false,
          "api_return_date": null,
          "api_return_qty": null,
          "api_source": "공공데이터포털 getLockUpRetuInfo_V3",
          "holder_name": null,
          "reason": null
        },
        {
          "period": "3개월",
          "date": "2026-09-29",
          "date_display": "2026-09-29",
          "tradable_date": "2026-09-29",
          "qty": 359161,
          "pct": 2.98,
          "type": "IPO확약",
          "category": "IPO기관",
          "status": "예정",
          "source": "DART",
          "source_label": "증권발행실적보고서",
          "rcp": "20260623000136",
          "api_checked": false,
          "api_return_date": null,
          "api_return_qty": null,
          "api_source": "공공데이터포털 getLockUpRetuInfo_V3",
          "holder_name": null,
          "reason": null
        },
        {
          "period": "3개월",
          "date": "2026-09-29",
          "date_display": "2026-09-29",
          "tradable_date": "2026-09-29",
          "qty": 48000,
          "pct": 0.4,
          "type": "보호예수",
          "category": "구주·보호예수",
          "status": "예정",
          "source": "투자설명서",
          "source_label": "투자설명서 유통가능 요약표",
          "rcp": "20260616000250",
          "api_checked": false,
          "api_return_date": null,
          "api_return_qty": null,
          "api_source": "공공데이터포털 getLockUpRetuInfo_V3",
          "holder_name": null,
          "reason": null
        },
        {
          "period": "6개월",
          "date": "2026-12-29",
          "date_display": "2026-12-29",
          "tradable_date": "2026-12-29",
          "qty": 192075,
          "pct": 1.59,
          "type": "IPO확약",
          "category": "IPO기관",
          "status": "예정",
          "source": "DART",
          "source_label": "증권발행실적보고서",
          "rcp": "20260623000136",
          "api_checked": false,
          "api_return_date": null,
          "api_return_qty": null,
          "api_source": "공공데이터포털 getLockUpRetuInfo_V3",
          "holder_name": null,
          "reason": null
        },
        {
          "period": "1년",
          "date": "2027-06-29",
          "date_display": "2027-06-29",
          "tradable_date": "2027-06-29",
          "qty": 770102,
          "pct": 6.39,
          "type": "보호예수",
          "category": "구주·보호예수",
          "status": "예정",
          "source": "투자설명서",
          "source_label": "투자설명서 유통가능 요약표",
          "rcp": "20260616000250",
          "api_checked": false,
          "api_return_date": null,
          "api_return_qty": null,
          "api_source": "공공데이터포털 getLockUpRetuInfo_V3",
          "holder_name": null,
          "reason": null
        },
        {
          "period": "2년",
          "date": "2028-06-29",
          "date_display": "2028-06-29",
          "tradable_date": "2028-06-29",
          "qty": 6177128,
          "pct": 51.26,
          "type": "보호예수",
          "category": "구주·보호예수",
          "status": "예정",
          "source": "투자설명서",
          "source_label": "투자설명서 유통가능 요약표",
          "rcp": "20260616000250",
          "api_checked": false,
          "api_return_date": null,
          "api_return_qty": null,
          "api_source": "공공데이터포털 getLockUpRetuInfo_V3",
          "holder_name": null,
          "reason": null
        }
      ],
      "holders": []
    },
    {
      "code": "475040",
      "name": "스트라드비젼",
      "market": "코스닥",
      "listing_date": "2026-06-30",
      "shares": 53255138,
      "close_price": 7200,
      "events": [
        {
          "period": "15일",
          "date": "2026-07-15",
          "date_display": "2026-07-15",
          "tradable_date": "2026-07-15",
          "qty": 189714,
          "pct": 0.36,
          "type": "IPO확약",
          "category": "IPO기관",
          "status": "예정",
          "source": "DART",
          "source_label": "증권발행실적보고서",
          "rcp": "20260623000422",
          "api_checked": false,
          "api_return_date": null,
          "api_return_qty": null,
          "api_source": "공공데이터포털 getLockUpRetuInfo_V3",
          "holder_name": null,
          "reason": null
        },
        {
          "period": "1개월",
          "date": "2026-07-30",
          "date_display": "2026-07-30",
          "tradable_date": "2026-07-30",
          "qty": 152248,
          "pct": 0.29,
          "type": "IPO확약",
          "category": "IPO기관",
          "status": "예정",
          "source": "DART",
          "source_label": "증권발행실적보고서",
          "rcp": "20260623000422",
          "api_checked": false,
          "api_return_date": null,
          "api_return_qty": null,
          "api_source": "공공데이터포털 getLockUpRetuInfo_V3",
          "holder_name": null,
          "reason": null
        },
        {
          "period": "3개월",
          "date": "2026-09-30",
          "date_display": "2026-09-30",
          "tradable_date": "2026-09-30",
          "qty": 99250,
          "pct": 0.19,
          "type": "IPO확약",
          "category": "IPO기관",
          "status": "예정",
          "source": "DART",
          "source_label": "증권발행실적보고서",
          "rcp": "20260623000422",
          "api_checked": false,
          "api_return_date": null,
          "api_return_qty": null,
          "api_source": "공공데이터포털 getLockUpRetuInfo_V3",
          "holder_name": null,
          "reason": null
        },
        {
          "period": "3개월",
          "date": "2026-09-30",
          "date_display": "2026-09-30",
          "tradable_date": "2026-09-30",
          "qty": 83333,
          "pct": 0.16,
          "type": "보호예수",
          "category": "구주·보호예수",
          "status": "예정",
          "source": "투자설명서",
          "source_label": "투자설명서 유통가능 요약표",
          "rcp": "20260617000171",
          "api_checked": false,
          "api_return_date": null,
          "api_return_qty": null,
          "api_source": "공공데이터포털 getLockUpRetuInfo_V3",
          "holder_name": null,
          "reason": "마지막 누적 유통가능 주식수가 KRX 상장주식수와 불일치"
        },
        {
          "period": "6개월",
          "date": "2026-12-30",
          "date_display": "2026-12-30",
          "tradable_date": "2026-12-30",
          "qty": 1271808,
          "pct": 2.39,
          "type": "IPO확약",
          "category": "IPO기관",
          "status": "예정",
          "source": "DART",
          "source_label": "증권발행실적보고서",
          "rcp": "20260623000422",
          "api_checked": false,
          "api_return_date": null,
          "api_return_qty": null,
          "api_source": "공공데이터포털 getLockUpRetuInfo_V3",
          "holder_name": null,
          "reason": null
        },
        {
          "period": "6개월",
          "date": "2026-12-30",
          "date_display": "2026-12-30",
          "tradable_date": "2026-12-30",
          "qty": 70000,
          "pct": 0.13,
          "type": "보호예수",
          "category": "구주·보호예수",
          "status": "예정",
          "source": "투자설명서",
          "source_label": "투자설명서 유통가능 요약표",
          "rcp": "20260617000171",
          "api_checked": false,
          "api_return_date": null,
          "api_return_qty": null,
          "api_source": "공공데이터포털 getLockUpRetuInfo_V3",
          "holder_name": null,
          "reason": "마지막 누적 유통가능 주식수가 KRX 상장주식수와 불일치"
        },
        {
          "period": "1년",
          "date": "2027-06-30",
          "date_display": "2027-06-30",
          "tradable_date": "2027-06-30",
          "qty": 707030,
          "pct": 1.33,
          "type": "보호예수",
          "category": "구주·보호예수",
          "status": "예정",
          "source": "투자설명서",
          "source_label": "투자설명서 유통가능 요약표",
          "rcp": "20260617000171",
          "api_checked": false,
          "api_return_date": null,
          "api_return_qty": null,
          "api_source": "공공데이터포털 getLockUpRetuInfo_V3",
          "holder_name": null,
          "reason": "마지막 누적 유통가능 주식수가 KRX 상장주식수와 불일치"
        },
        {
          "period": "3년",
          "date": "2029-06-30",
          "date_display": "2029-06-30",
          "tradable_date": "2029-06-30",
          "qty": 26382611,
          "pct": 49.54,
          "type": "보호예수",
          "category": "구주·보호예수",
          "status": "예정",
          "source": "투자설명서",
          "source_label": "투자설명서 유통가능 요약표",
          "rcp": "20260617000171",
          "api_checked": false,
          "api_return_date": null,
          "api_return_qty": null,
          "api_source": "공공데이터포털 getLockUpRetuInfo_V3",
          "holder_name": null,
          "reason": "마지막 누적 유통가능 주식수가 KRX 상장주식수와 불일치"
        }
      ],
      "holders": []
    },
    {
      "code": "0039P0",
      "name": "매드업",
      "market": "코스닥",
      "listing_date": "2026-07-01",
      "shares": 18746800,
      "close_price": 10080,
      "events": [
        {
          "period": "15일",
          "date": "2026-07-16",
          "date_display": "2026-07-16",
          "tradable_date": "2026-07-16",
          "qty": 488053,
          "pct": 2.6,
          "type": "IPO확약",
          "category": "IPO기관",
          "status": "예정",
          "source": "DART",
          "source_label": "증권발행실적보고서",
          "rcp": "20260626000469",
          "api_checked": false,
          "api_return_date": null,
          "api_return_qty": null,
          "api_source": "공공데이터포털 getLockUpRetuInfo_V3",
          "holder_name": null,
          "reason": null
        },
        {
          "period": "1개월",
          "date": "2026-08-01",
          "date_display": "2026-08-01",
          "tradable_date": "2026-08-01",
          "qty": 142214,
          "pct": 0.76,
          "type": "IPO확약",
          "category": "IPO기관",
          "status": "예정",
          "source": "DART",
          "source_label": "증권발행실적보고서",
          "rcp": "20260626000469",
          "api_checked": false,
          "api_return_date": null,
          "api_return_qty": null,
          "api_source": "공공데이터포털 getLockUpRetuInfo_V3",
          "holder_name": null,
          "reason": null
        },
        {
          "period": "1개월",
          "date": "2026-08-01",
          "date_display": "2026-08-01",
          "tradable_date": "2026-08-01",
          "qty": 2563800,
          "pct": 13.68,
          "type": "보호예수",
          "category": "구주·보호예수",
          "status": "예정",
          "source": "투자설명서",
          "source_label": "투자설명서 유통가능 요약표",
          "rcp": "20260622000384",
          "api_checked": false,
          "api_return_date": null,
          "api_return_qty": null,
          "api_source": "공공데이터포털 getLockUpRetuInfo_V3",
          "holder_name": null,
          "reason": null
        },
        {
          "period": "3개월",
          "date": "2026-10-01",
          "date_display": "2026-10-01",
          "tradable_date": "2026-10-01",
          "qty": 452412,
          "pct": 2.41,
          "type": "IPO확약",
          "category": "IPO기관",
          "status": "예정",
          "source": "DART",
          "source_label": "증권발행실적보고서",
          "rcp": "20260626000469",
          "api_checked": false,
          "api_return_date": null,
          "api_return_qty": null,
          "api_source": "공공데이터포털 getLockUpRetuInfo_V3",
          "holder_name": null,
          "reason": null
        },
        {
          "period": "3개월",
          "date": "2026-10-01",
          "date_display": "2026-10-01",
          "tradable_date": "2026-10-01",
          "qty": 1898200,
          "pct": 10.13,
          "type": "보호예수",
          "category": "구주·보호예수",
          "status": "예정",
          "source": "투자설명서",
          "source_label": "투자설명서 유통가능 요약표",
          "rcp": "20260622000384",
          "api_checked": false,
          "api_return_date": null,
          "api_return_qty": null,
          "api_source": "공공데이터포털 getLockUpRetuInfo_V3",
          "holder_name": null,
          "reason": null
        },
        {
          "period": "6개월",
          "date": "2027-01-01",
          "date_display": "2027-01-01",
          "tradable_date": "2027-01-01",
          "qty": 164476,
          "pct": 0.88,
          "type": "IPO확약",
          "category": "IPO기관",
          "status": "예정",
          "source": "DART",
          "source_label": "증권발행실적보고서",
          "rcp": "20260626000469",
          "api_checked": false,
          "api_return_date": null,
          "api_return_qty": null,
          "api_source": "공공데이터포털 getLockUpRetuInfo_V3",
          "holder_name": null,
          "reason": null
        },
        {
          "period": "6개월",
          "date": "2027-01-01",
          "date_display": "2027-01-01",
          "tradable_date": "2027-01-01",
          "qty": 840400,
          "pct": 4.48,
          "type": "보호예수",
          "category": "구주·보호예수",
          "status": "예정",
          "source": "투자설명서",
          "source_label": "투자설명서 유통가능 요약표",
          "rcp": "20260622000384",
          "api_checked": false,
          "api_return_date": null,
          "api_return_qty": null,
          "api_source": "공공데이터포털 getLockUpRetuInfo_V3",
          "holder_name": null,
          "reason": null
        },
        {
          "period": "1년",
          "date": "2027-07-01",
          "date_display": "2027-07-01",
          "tradable_date": "2027-07-01",
          "qty": 421900,
          "pct": 2.25,
          "type": "보호예수",
          "category": "구주·보호예수",
          "status": "예정",
          "source": "투자설명서",
          "source_label": "투자설명서 유통가능 요약표",
          "rcp": "20260622000384",
          "api_checked": false,
          "api_return_date": null,
          "api_return_qty": null,
          "api_source": "공공데이터포털 getLockUpRetuInfo_V3",
          "holder_name": null,
          "reason": null
        },
        {
          "period": "2년",
          "date": "2028-07-01",
          "date_display": "2028-07-01",
          "tradable_date": "2028-07-01",
          "qty": 7236000,
          "pct": 38.6,
          "type": "보호예수",
          "category": "구주·보호예수",
          "status": "예정",
          "source": "투자설명서",
          "source_label": "투자설명서 유통가능 요약표",
          "rcp": "20260622000384",
          "api_checked": false,
          "api_return_date": null,
          "api_return_qty": null,
          "api_source": "공공데이터포털 getLockUpRetuInfo_V3",
          "holder_name": null,
          "reason": null
        }
      ],
      "holders": []
    },
    {
      "code": "365660",
      "name": "레몬헬스케어",
      "market": "코스닥",
      "listing_date": "2026-07-06",
      "shares": 13351559,
      "close_price": 9400,
      "events": [
        {
          "period": "15일",
          "date": "2026-07-21",
          "date_display": "2026-07-21",
          "tradable_date": "2026-07-21",
          "qty": 724123,
          "pct": 5.42,
          "type": "IPO확약",
          "category": "IPO기관",
          "status": "예정",
          "source": "DART",
          "source_label": "증권발행실적보고서",
          "rcp": "20260629000505",
          "api_checked": false,
          "api_return_date": null,
          "api_return_qty": null,
          "api_source": "공공데이터포털 getLockUpRetuInfo_V3",
          "holder_name": null,
          "reason": null
        },
        {
          "period": "1개월",
          "date": "2026-08-06",
          "date_display": "2026-08-06",
          "tradable_date": "2026-08-06",
          "qty": 91938,
          "pct": 0.69,
          "type": "IPO확약",
          "category": "IPO기관",
          "status": "예정",
          "source": "DART",
          "source_label": "증권발행실적보고서",
          "rcp": "20260629000505",
          "api_checked": false,
          "api_return_date": null,
          "api_return_qty": null,
          "api_source": "공공데이터포털 getLockUpRetuInfo_V3",
          "holder_name": null,
          "reason": null
        },
        {
          "period": "1개월",
          "date": "2026-08-06",
          "date_display": "2026-08-06",
          "tradable_date": "2026-08-06",
          "qty": 2391012,
          "pct": 17.91,
          "type": "보호예수",
          "category": "구주·보호예수",
          "status": "예정",
          "source": "투자설명서",
          "source_label": "투자설명서 유통가능 요약표",
          "rcp": "20260623000244",
          "api_checked": false,
          "api_return_date": null,
          "api_return_qty": null,
          "api_source": "공공데이터포털 getLockUpRetuInfo_V3",
          "holder_name": null,
          "reason": "마지막 누적 유통가능 주식수가 KRX 상장주식수와 불일치"
        },
        {
          "period": "3개월",
          "date": "2026-10-06",
          "date_display": "2026-10-06",
          "tradable_date": "2026-10-06",
          "qty": 2447012,
          "pct": 18.33,
          "type": "보호예수",
          "category": "구주·보호예수",
          "status": "예정",
          "source": "투자설명서",
          "source_label": "투자설명서 유통가능 요약표",
          "rcp": "20260623000244",
          "api_checked": false,
          "api_return_date": null,
          "api_return_qty": null,
          "api_source": "공공데이터포털 getLockUpRetuInfo_V3",
          "holder_name": null,
          "reason": "마지막 누적 유통가능 주식수가 KRX 상장주식수와 불일치"
        },
        {
          "period": "6개월",
          "date": "2027-01-06",
          "date_display": "2027-01-06",
          "tradable_date": "2027-01-06",
          "qty": 296514,
          "pct": 2.22,
          "type": "IPO확약",
          "category": "IPO기관",
          "status": "예정",
          "source": "DART",
          "source_label": "증권발행실적보고서",
          "rcp": "20260629000505",
          "api_checked": false,
          "api_return_date": null,
          "api_return_qty": null,
          "api_source": "공공데이터포털 getLockUpRetuInfo_V3",
          "holder_name": null,
          "reason": null
        },
        {
          "period": "1년",
          "date": "2027-07-06",
          "date_display": "2027-07-06",
          "tradable_date": "2027-07-06",
          "qty": 90500,
          "pct": 0.68,
          "type": "보호예수",
          "category": "구주·보호예수",
          "status": "예정",
          "source": "투자설명서",
          "source_label": "투자설명서 유통가능 요약표",
          "rcp": "20260623000244",
          "api_checked": false,
          "api_return_date": null,
          "api_return_qty": null,
          "api_source": "공공데이터포털 getLockUpRetuInfo_V3",
          "holder_name": null,
          "reason": "마지막 누적 유통가능 주식수가 KRX 상장주식수와 불일치"
        },
        {
          "period": "2년",
          "date": "2028-07-06",
          "date_display": "2028-07-06",
          "tradable_date": "2028-07-06",
          "qty": 457495,
          "pct": 3.43,
          "type": "보호예수",
          "category": "구주·보호예수",
          "status": "예정",
          "source": "투자설명서",
          "source_label": "투자설명서 유통가능 요약표",
          "rcp": "20260623000244",
          "api_checked": false,
          "api_return_date": null,
          "api_return_qty": null,
          "api_source": "공공데이터포털 getLockUpRetuInfo_V3",
          "holder_name": null,
          "reason": "마지막 누적 유통가능 주식수가 KRX 상장주식수와 불일치"
        },
        {
          "period": "3년",
          "date": "2029-07-06",
          "date_display": "2029-07-06",
          "tradable_date": "2029-07-06",
          "qty": 3738120,
          "pct": 28.0,
          "type": "보호예수",
          "category": "구주·보호예수",
          "status": "예정",
          "source": "투자설명서",
          "source_label": "투자설명서 유통가능 요약표",
          "rcp": "20260623000244",
          "api_checked": false,
          "api_return_date": null,
          "api_return_qty": null,
          "api_source": "공공데이터포털 getLockUpRetuInfo_V3",
          "holder_name": null,
          "reason": "마지막 누적 유통가능 주식수가 KRX 상장주식수와 불일치"
        }
      ],
      "holders": []
    }
  ]
}